cardano_tools/__init__.py
cardano_tools/cli_tools.py
cardano_tools/node_tools.py
cardano_tools/utils/__init__.py
cardano_tools/utils/bech32.py
cardano_tools/wallet_tools.py
cardano_tools-2.0.1.dist-info/WHEEL
cardano_tools-2.0.1.dist-info/METADATA
cardano_tools-2.0.1.dist-info/RECORD
